{
    "title": {
        "eng": "MIRACLE WAVE"
    },
    "featured": true,
    "mv": "https://www.youtube.com/watch?v=xvL26PZ2qlQ",
    "credits": {
        "writer": "Aki Hata",
        "composer": "Takuya Sakai",
        "arranger": "Masatomi Waki",
        "singer": [
            "Aqours"
        ]
    },
    "lyrics": {
        "eng": "https://loveliveapi.herokuapp.com/api/storage/songs/miracle-wave-eng.txt",
        "kan": "https://loveliveapi.herokuapp.com/api/storage/songs/miracle-wave-kan.txt",
        "rom": "https://loveliveapi.herokuapp.com/api/storage/songs/miracle-wave-rom.txt"
    }
}